ffix/__init__.py
ffix/cli.py
ffix-0.0.3.dist-info/METADATA
ffix-0.0.3.dist-info/WHEEL
ffix-0.0.3.dist-info/entry_points.txt
ffix-0.0.3.dist-info/licenses/LICENSE
ffix-0.0.3.dist-info/RECORD
