Metadata-Version: 2.4
Name: ffix
Version: 0.0.3
Summary: Remux video files using ffmpeg
Project-URL: Homepage, https://github.com/aillt/ffix
Project-URL: License, https://github.com/aillt/ffix/blob/master/LICENSE
Author-email: aillt <aillt2@proton.me>
License: MIT License
License-File: LICENSE
Keywords: cli,codec,ffmpeg,remux,video
Classifier: License :: OSI Approved :: MIT License
Classifier: Operating System :: OS Independent
Classifier: Programming Language :: Python :: 3
Classifier: Programming Language :: Python :: 3.12
Requires-Python: >=3.12
Requires-Dist: rich>=14.0.0
Requires-Dist: typer>=0.15.2
